pyhun.py
pyhun-1.1.0.dist-info/LICENSE
pyhun-1.1.0.dist-info/METADATA
pyhun-1.1.0.dist-info/WHEEL
pyhun-1.1.0.dist-info/top_level.txt
pyhun-1.1.0.dist-info/RECORD
