Metadata-Version: 2.2
Name: pyhun
Version: 1.1.0
Summary: A Python package to generate Hugarian things
Author-email: Pőcze Bence <bence@pocze.ch>
License: MIT License
Requires-Python: >=3.8
License-File: LICENSE
Provides-Extra: dev
Requires-Dist: pytest; extra == "dev"
Requires-Dist: black; extra == "dev"
Requires-Dist: flake8; extra == "dev"
